{
    "version": "26.5.5",
    "description": "Open Source Identity and Access Management",
    "homepage": "https://www.keycloak.org/",
    "license": "Apache-2.0",
    "architecture": {
        "64bit": {
            "url": "https://github.com/keycloak/keycloak/releases/download/26.5.5/keycloak-26.5.5.zip",
            "hash": "5cd606f5e23ff77d9991ce55bab4a2ea529f05f7e16e24c1f270c6f360b50988"
        }
    },
    "extract_dir": "keycloak-26.5.5",
    "bin": [
        [
            "bin/kc.sh",
            "kc"
        ]
    ],
    "suggest": {
        "JDK": "java/openjdk"
    },
    "checkver": {
        "github": "https://github.com/keycloak/keycloak"
    },
    "autoupdate": {
        "architecture": {
            "64bit": {
                "url": "https://github.com/keycloak/keycloak/releases/download/$version/keycloak-$version.zip"
            }
        },
        "extract_dir": "keycloak-$version"
    }
}
